utilyzer/__init__.py
utilyzer/date_utils.py
utilyzer/py.typed
utilyzer/str_to_number.py
utilyzer-0.0.3.dist-info/METADATA
utilyzer-0.0.3.dist-info/WHEEL
utilyzer-0.0.3.dist-info/licenses/LICENSE
utilyzer-0.0.3.dist-info/RECORD
