Metadata-Version: 2.3
Name: utilyzer
Version: 0.0.3
Summary: A tool for awesome python utils
Project-URL: Documentation, https://asmitul.github.io/utilyzer
Project-URL: Issues, https://github.com/asmitul/utilyzer/issues
Project-URL: Source, https://github.com/asmitul/utilyzer
Author: asmitul
License: MIT
Classifier: Development Status :: 4 - Beta
Classifier: Intended Audience :: Developers
Classifier: License :: OSI Approved :: MIT License
Classifier: Programming Language :: Python
Classifier: Programming Language :: Python :: 3.8
Classifier: Programming Language :: Python :: 3.9
Classifier: Programming Language :: Python :: 3.10
Classifier: Programming Language :: Python :: 3.11
Classifier: Programming Language :: Python :: Implementation :: CPython
Classifier: Programming Language :: Python :: Implementation :: PyPy
Classifier: Topic :: Internet
Classifier: Topic :: Software Development
Classifier: Topic :: Software Development :: Libraries
Classifier: Topic :: Software Development :: Libraries :: Application Frameworks
Classifier: Topic :: Software Development :: Libraries :: Python Modules
Requires-Python: <3.12,>=3.8
Requires-Dist: pytz
Requires-Dist: types-pytz
Provides-Extra: docs
Requires-Dist: mkdocs-git-revision-date-localized-plugin~=1.3.0; extra == 'docs'
Requires-Dist: mkdocs-material~=9.5.48; extra == 'docs'
Requires-Dist: mkdocstrings[python]~=0.27.0; extra == 'docs'
Requires-Dist: mkdocs~=1.6.1; extra == 'docs'
Provides-Extra: quality
Requires-Dist: black~=24.10.0; extra == 'quality'
Requires-Dist: mypy~=1.13.0; extra == 'quality'
Requires-Dist: pre-commit~=4.0.1; extra == 'quality'
Requires-Dist: ruff~=0.8.2; extra == 'quality'
Provides-Extra: tests
Requires-Dist: pytest-cov~=6.0.0; extra == 'tests'
Requires-Dist: pytest~=8.3.4; extra == 'tests'
